juzi/__init__.py
juzi/cs/__init__.py
juzi/cs/_cluster.py
juzi/cs/_nmf.py
juzi/cs/_plot.py
juzi/cs/_prune.py
juzi/cs/_similarity.py
juzi/ct/__init__.py
juzi/ct/models.py
juzi/mg/__init__.py
juzi/mg/cancer_breast.json
juzi/mg/cancer_pathways.json
juzi/mg/cell_cycle.json
juzi-0.1.3.dist-info/METADATA
juzi-0.1.3.dist-info/WHEEL
juzi-0.1.3.dist-info/licenses/LICENSE.txt
juzi-0.1.3.dist-info/RECORD
