Metadata-Version: 2.4
Name: juzi
Version: 0.1.3
Summary: juzi
Project-URL: Homepage, https://github.com/tomouellette/juzi
Project-URL: Issues, https://github.com/tomouellette/juzi/issues
Author: Tom W. Ouellette
License-File: LICENSE.txt
Requires-Python: >=3.11
Requires-Dist: anndata
Requires-Dist: glasbey
Requires-Dist: joblib
Requires-Dist: matplotlib
Requires-Dist: numpy
Requires-Dist: scipy
Requires-Dist: torch
Requires-Dist: tqdm
